MHCInc/GuessGame.py
MHCInc/GuessGameEasy.py
MHCInc/GuessGameSecondary.py
MHCInc/MITLicense.py
MHCInc/PHYSICAL_CONDITION_APPLET.py
MHCInc/Python3学习示例.py
MHCInc/__init__.py
MHCInc/animal_guess.py
MHCInc/caterpillar.py
MHCInc/caterpillar2.py
MHCInc/copyright.py
MHCInc/egg_catcher.py
MHCInc/egg_catcher_perfect.py
MHCInc/matchmaker.py
MHCInc/random.py
MHCInc/rectangle.py
MHCInc/robot_builder.py
MHCInc/screen_pet.py
MHCInc/swift.py
MHCInc/加密消息.py
MHCInc/单词九连猜.py
MHCInc/圆筒万花筒.py
MHCInc/快照抓拍.py
MHCInc/星光夜空.py
MHCInc/螺旋万花筒.py
MHCInc-0.2.4.dist-info/LICENSE.txt
MHCInc-0.2.4.dist-info/METADATA
MHCInc-0.2.4.dist-info/WHEEL
MHCInc-0.2.4.dist-info/top_level.txt
MHCInc-0.2.4.dist-info/RECORD
