Metadata-Version: 2.1
Name: MHCInc
Version: 0.2.4
Summary: 改进漏洞：重复模块引用时无法配置删除的环境，使用MHCInc.module.setup()即可
Home-page: https://pypi.org/project/MHCInc/
Author: Mhc-inc
Author-email: Wf6350177@163.com
Project-URL: Bug Tracker, https://github.com/Mhc-inc/MHCInc/issues
Classifier: Programming Language :: Python :: 3
Classifier: License :: OSI Approved :: MIT License
Classifier: Operating System :: OS Independent
Requires-Python: >=3.9
License-File: LICENSE.txt
